lockexclusive/LICENSE
lockexclusive/README.md
lockexclusive/__init__.py
lockexclusive/requirements.txt
lockexclusive/thirdparty.json
lockexclusive-0.10.dist-info/LICENSE.rst
lockexclusive-0.10.dist-info/METADATA
lockexclusive-0.10.dist-info/WHEEL
lockexclusive-0.10.dist-info/top_level.txt
lockexclusive-0.10.dist-info/RECORD
