Metadata-Version: 2.1
Name: lockexclusive
Version: 0.10
Summary: Limits the number of running instances of a Python script
Home-page: https://github.com/hansalemaos/lockexclusive
Author: Johannes Fischer
Author-email: aulasparticularesdealemaosp@gmail.com
License: MIT
Keywords: limit,instances
Classifier: Development Status :: 4 - Beta
Classifier: Programming Language :: Python :: 3 :: Only
Classifier: Programming Language :: Python :: 3.10
Classifier: Topic :: Software Development :: Libraries :: Python Modules
Classifier: Topic :: Utilities
License-File: LICENSE.rst
